<playlist version="1" xmlns="http://xspf.org/ns/0/"> 
  <title>ArtOnAir.org :: ART INTERNATIONAL RADIO -  </title> 
  <image>http://www.artonair.org/images/art_radio_logo.png</image>
  <info>http://www.artonair.org</info>
  <annotation>ART INTERNATIONAL RADIO PLAYLIST</annotation>
 
  <tracklist>
 
   <item> 
    <title>Afronetic -RoFlav pep remix: Romain</title>
    <location>http://www.artonair.org/archives/mp3/sbmhopper14_tk01.mp3</location>
   </item> 
 
   <item> 
    <title>Live In the Light: Jaymz Nylon</title>
    <location>http://www.artonair.org/archives/mp3/sbmhopper14_tk02.mp3</location>
   </item> 
 
   <item> 
    <title>Groove in My Mind -Hellex M remix: Salvatore Agrosi &amp; Fast Vision Soul</title>
    <location>http://www.artonair.org/archives/mp3/sbmhopper14_tk03.mp3</location>
   </item> 
 
   <item> 
    <title>Wonder Why: Hand Grenade Pimps</title>
    <location>http://www.artonair.org/archives/mp3/sbmhopper14_tk04.mp3</location>
   </item> 
 
   <item> 
    <title>Let It Blow -Dubtrumental: Shane D</title>
    <location>http://www.artonair.org/archives/mp3/sbmhopper14_tk05.mp3</location>
   </item> 
 
   <item> 
    <title>Passionardor: Passionardor</title>
    <location>http://www.artonair.org/archives/mp3/sbmhopper14_tk06.mp3</location>
   </item> 
 
   <item> 
    <title>The White Light -Afro Mix: Groove Junkies ft Alexander Sky</title>
    <location>http://www.artonair.org/archives/mp3/sbmhopper14_tk07.mp3</location>
   </item> 
 
   <item> 
    <title>Move On -Groove Junkies MoHo remix: Fleetside ft Carolyn Harding</title>
    <location>http://www.artonair.org/archives/mp3/sbmhopper14_tk08.mp3</location>
   </item> 
 
   <item> 
    <title>My Cry -Davidson Ospina Athem remix: Inaya Day</title>
    <location>http://www.artonair.org/archives/mp3/sbmhopper14_tk09.mp3</location>
   </item> 
 
   <item> 
    <title>It's About You: Mr.V</title>
    <location>http://www.artonair.org/archives/mp3/sbmhopper14_tk10.mp3</location>
   </item> 
 
   <item> 
    <title>Water Waves -Powerline mix: Wil Milton</title>
    <location>http://www.artonair.org/archives/mp3/sbmhopper14_tk11.mp3</location>
   </item> 
 
   <item> 
    <title>Everything is Happening at the Same Time -Atnarko remix: Hawke</title>
    <location>http://www.artonair.org/archives/mp3/sbmhopper14_tk12.mp3</location>
   </item> 
 
 </tracklist> 
</playlist> 
